odoo/addons/crm_phonecall_summary_predefined/README.rst
odoo/addons/crm_phonecall_summary_predefined/__init__.py
odoo/addons/crm_phonecall_summary_predefined/__manifest__.py
odoo/addons/crm_phonecall_summary_predefined/hooks.py
odoo/addons/crm_phonecall_summary_predefined/i18n/am.po
odoo/addons/crm_phonecall_summary_predefined/i18n/ar.po
odoo/addons/crm_phonecall_summary_predefined/i18n/bg.po
odoo/addons/crm_phonecall_summary_predefined/i18n/bs.po
odoo/addons/crm_phonecall_summary_predefined/i18n/ca.po
odoo/addons/crm_phonecall_summary_predefined/i18n/crm_phonecall_summary_predefined.pot
odoo/addons/crm_phonecall_summary_predefined/i18n/cs.po
odoo/addons/crm_phonecall_summary_predefined/i18n/da.po
odoo/addons/crm_phonecall_summary_predefined/i18n/de.po
odoo/addons/crm_phonecall_summary_predefined/i18n/el_GR.po
odoo/addons/crm_phonecall_summary_predefined/i18n/en_GB.po
odoo/addons/crm_phonecall_summary_predefined/i18n/es.po
odoo/addons/crm_phonecall_summary_predefined/i18n/es_AR.po
odoo/addons/crm_phonecall_summary_predefined/i18n/es_CL.po
odoo/addons/crm_phonecall_summary_predefined/i18n/es_CO.po
odoo/addons/crm_phonecall_summary_predefined/i18n/es_CR.po
odoo/addons/crm_phonecall_summary_predefined/i18n/es_DO.po
odoo/addons/crm_phonecall_summary_predefined/i18n/es_EC.po
odoo/addons/crm_phonecall_summary_predefined/i18n/es_ES.po
odoo/addons/crm_phonecall_summary_predefined/i18n/es_MX.po
odoo/addons/crm_phonecall_summary_predefined/i18n/es_PE.po
odoo/addons/crm_phonecall_summary_predefined/i18n/es_PY.po
odoo/addons/crm_phonecall_summary_predefined/i18n/es_VE.po
odoo/addons/crm_phonecall_summary_predefined/i18n/et.po
odoo/addons/crm_phonecall_summary_predefined/i18n/eu.po
odoo/addons/crm_phonecall_summary_predefined/i18n/fa.po
odoo/addons/crm_phonecall_summary_predefined/i18n/fi.po
odoo/addons/crm_phonecall_summary_predefined/i18n/fr.po
odoo/addons/crm_phonecall_summary_predefined/i18n/fr_CA.po
odoo/addons/crm_phonecall_summary_predefined/i18n/fr_CH.po
odoo12_addon_crm_phonecall_summary_predefined-12.0.1.0.0.99.dev20.dist-info/METADATA
odoo12_addon_crm_phonecall_summary_predefined-12.0.1.0.0.99.dev20.dist-info/WHEEL
odoo12_addon_crm_phonecall_summary_predefined-12.0.1.0.0.99.dev20.dist-info/top_level.txt
odoo12_addon_crm_phonecall_summary_predefined-12.0.1.0.0.99.dev20.dist-info/RECORD
